dragoneye/__init__.py
dragoneye/classification.py
dragoneye/client.py
dragoneye/constants.py
dragoneye/models.py
dragoneye/types/__init__.py
dragoneye/types/common.py
dragoneye/types/exception.py
dragoneye/types/media.py
dragoneye_python-0.4.1.dist-info/METADATA
dragoneye_python-0.4.1.dist-info/WHEEL
dragoneye_python-0.4.1.dist-info/top_level.txt
dragoneye_python-0.4.1.dist-info/RECORD
